{"kind":"enum","display_name":"DyeColor","extra":{"bracket_enum":"minecraft:dye_color","loaders":["crafttweaker"]},"key":"vanilla/api/item/component/DyeColor","members":{"BLACK":{"key":"BLACK","members":[{"kind":"enum_constant","display_name":"BLACK","extra":{},"key":"BLACK","origin":"inherited","static":true,"type":{"kind":"java","class_name":"DyeColor","display_name":"DyeColor","interfaces":[],"key":"net.minecraft.world.item.DyeColor","nullable":false,"package_name":"net.minecraft.world.item","type_parameters":{}}}]},"BLUE":{"key":"BLUE","members":[{"kind":"enum_constant","display_name":"BLUE","extra":{},"key":"BLUE","origin":"inherited","static":true,"type":{"kind":"java","class_name":"DyeColor","display_name":"DyeColor","interfaces":[],"key":"net.minecraft.world.item.DyeColor","nullable":false,"package_name":"net.minecraft.world.item","type_parameters":{}}}]},"BROWN":{"key":"BROWN","members":[{"kind":"enum_constant","display_name":"BROWN","extra":{},"key":"BROWN","origin":"inherited","static":true,"type":{"kind":"java","class_name":"DyeColor","display_name":"DyeColor","interfaces":[],"key":"net.minecraft.world.item.DyeColor","nullable":false,"package_name":"net.minecraft.world.item","type_parameters":{}}}]},"CYAN":{"key":"CYAN","members":[{"kind":"enum_constant","display_name":"CYAN","extra":{},"key":"CYAN","origin":"inherited","static":true,"type":{"kind":"java","class_name":"DyeColor","display_name":"DyeColor","interfaces":[],"key":"net.minecraft.world.item.DyeColor","nullable":false,"package_name":"net.minecraft.world.item","type_parameters":{}}}]},"GRAY":{"key":"GRAY","members":[{"kind":"enum_constant","display_name":"GRAY","extra":{},"key":"GRAY","origin":"inherited","static":true,"type":{"kind":"java","class_name":"DyeColor","display_name":"DyeColor","interfaces":[],"key":"net.minecraft.world.item.DyeColor","nullable":false,"package_name":"net.minecraft.world.item","type_parameters":{}}}]},"GREEN":{"key":"GREEN","members":[{"kind":"enum_constant","display_name":"GREEN","extra":{},"key":"GREEN","origin":"inherited","static":true,"type":{"kind":"java","class_name":"DyeColor","display_name":"DyeColor","interfaces":[],"key":"net.minecraft.world.item.DyeColor","nullable":false,"package_name":"net.minecraft.world.item","type_parameters":{}}}]},"LIGHT_BLUE":{"key":"LIGHT_BLUE","members":[{"kind":"enum_constant","display_name":"LIGHT_BLUE","extra":{},"key":"LIGHT_BLUE","origin":"inherited","static":true,"type":{"kind":"java","class_name":"DyeColor","display_name":"DyeColor","interfaces":[],"key":"net.minecraft.world.item.DyeColor","nullable":false,"package_name":"net.minecraft.world.item","type_parameters":{}}}]},"LIGHT_GRAY":{"key":"LIGHT_GRAY","members":[{"kind":"enum_constant","display_name":"LIGHT_GRAY","extra":{},"key":"LIGHT_GRAY","origin":"inherited","static":true,"type":{"kind":"java","class_name":"DyeColor","display_name":"DyeColor","interfaces":[],"key":"net.minecraft.world.item.DyeColor","nullable":false,"package_name":"net.minecraft.world.item","type_parameters":{}}}]},"LIME":{"key":"LIME","members":[{"kind":"enum_constant","display_name":"LIME","extra":{},"key":"LIME","origin":"inherited","static":true,"type":{"kind":"java","class_name":"DyeColor","display_name":"DyeColor","interfaces":[],"key":"net.minecraft.world.item.DyeColor","nullable":false,"package_name":"net.minecraft.world.item","type_parameters":{}}}]},"MAGENTA":{"key":"MAGENTA","members":[{"kind":"enum_constant","display_name":"MAGENTA","extra":{},"key":"MAGENTA","origin":"inherited","static":true,"type":{"kind":"java","class_name":"DyeColor","display_name":"DyeColor","interfaces":[],"key":"net.minecraft.world.item.DyeColor","nullable":false,"package_name":"net.minecraft.world.item","type_parameters":{}}}]},"ORANGE":{"key":"ORANGE","members":[{"kind":"enum_constant","display_name":"ORANGE","extra":{},"key":"ORANGE","origin":"inherited","static":true,"type":{"kind":"java","class_name":"DyeColor","display_name":"DyeColor","interfaces":[],"key":"net.minecraft.world.item.DyeColor","nullable":false,"package_name":"net.minecraft.world.item","type_parameters":{}}}]},"PINK":{"key":"PINK","members":[{"kind":"enum_constant","display_name":"PINK","extra":{},"key":"PINK","origin":"inherited","static":true,"type":{"kind":"java","class_name":"DyeColor","display_name":"DyeColor","interfaces":[],"key":"net.minecraft.world.item.DyeColor","nullable":false,"package_name":"net.minecraft.world.item","type_parameters":{}}}]},"PURPLE":{"key":"PURPLE","members":[{"kind":"enum_constant","display_name":"PURPLE","extra":{},"key":"PURPLE","origin":"inherited","static":true,"type":{"kind":"java","class_name":"DyeColor","display_name":"DyeColor","interfaces":[],"key":"net.minecraft.world.item.DyeColor","nullable":false,"package_name":"net.minecraft.world.item","type_parameters":{}}}]},"RED":{"key":"RED","members":[{"kind":"enum_constant","display_name":"RED","extra":{},"key":"RED","origin":"inherited","static":true,"type":{"kind":"java","class_name":"DyeColor","display_name":"DyeColor","interfaces":[],"key":"net.minecraft.world.item.DyeColor","nullable":false,"package_name":"net.minecraft.world.item","type_parameters":{}}}]},"WHITE":{"key":"WHITE","members":[{"kind":"enum_constant","display_name":"WHITE","extra":{},"key":"WHITE","origin":"inherited","static":true,"type":{"kind":"java","class_name":"DyeColor","display_name":"DyeColor","interfaces":[],"key":"net.minecraft.world.item.DyeColor","nullable":false,"package_name":"net.minecraft.world.item","type_parameters":{}}}]},"YELLOW":{"key":"YELLOW","members":[{"kind":"enum_constant","display_name":"YELLOW","extra":{},"key":"YELLOW","origin":"inherited","static":true,"type":{"kind":"java","class_name":"DyeColor","display_name":"DyeColor","interfaces":[],"key":"net.minecraft.world.item.DyeColor","nullable":false,"package_name":"net.minecraft.world.item","type_parameters":{}}}]},"fireworkColor":{"key":"fireworkColor","members":[{"kind":"getter","comment":{"kind":"root","children":[{"kind":"plaintext","content":"Gets the firework color of the DyeColor."}]},"display_name":"fireworkColor","extra":{"returns":{"kind":"root","children":[{"kind":"plaintext","content":"The firework color of the DyeColor."}]}},"key":"fireworkColor","origin":"native","static":false,"type":{"kind":"basic","display_name":"int","key":"int","nullable":false}}]},"serializedName":{"key":"serializedName","members":[{"kind":"method","comment":{"kind":"root","children":[{"kind":"plaintext","content":"Gets the serialized name."}]},"display_name":"serializedName","extra":{"returns":{"kind":"root","children":[{"kind":"plaintext","content":"the serialized name."}]}},"key":"serializedName","origin":"native","parameters":[],"return_type":{"kind":"basic","display_name":"string","key":"java.lang.String","nullable":false},"static":false,"type_parameters":{}},{"kind":"getter","comment":{"kind":"root","children":[{"kind":"plaintext","content":"Gets the serialized name."}]},"display_name":"serializedName","extra":{"returns":{"kind":"root","children":[{"kind":"plaintext","content":"the serialized name."}]}},"key":"serializedName","origin":"native","static":false,"type":{"kind":"basic","display_name":"string","key":"java.lang.String","nullable":false}}]},"textColor":{"key":"textColor","members":[{"kind":"getter","comment":{"kind":"root","children":[{"kind":"plaintext","content":"Gets the text color of the DyeColor."}]},"display_name":"textColor","extra":{"returns":{"kind":"root","children":[{"kind":"plaintext","content":"The text color of the DyeColor."}]}},"key":"textColor","origin":"native","static":false,"type":{"kind":"basic","display_name":"int","key":"int","nullable":false}}]}},"type":{"kind":"java","class_name":"DyeColor","display_name":"DyeColor","interfaces":[{"kind":"java","class_name":"StringRepresentable","display_name":"StringRepresentable","interfaces":[],"key":"net.minecraft.util.StringRepresentable","nullable":false,"package_name":"net.minecraft.util","type_parameters":{}},{"kind":"java","class_name":"Comparable","display_name":"Comparable\u003cE : Enum\u003e","interfaces":[],"key":"java.lang.Comparable","nullable":false,"package_name":"java.lang","type_parameters":{"T":{"kind":"generic","bound":"upper","display_name":"E","key":"E","nullable":false,"type":{"kind":"java","class_name":"Enum","display_name":"Enum\u003cE : Enum\u003e","interfaces":[],"key":"java.lang.Enum","nullable":false,"package_name":"java.lang","type_parameters":{}}}}}],"key":"net.minecraft.world.item.DyeColor","nullable":false,"package_name":"net.minecraft.world.item","super_type":{"kind":"java","class_name":"Enum","display_name":"Enum\u003cDyeColor\u003e","interfaces":[],"key":"java.lang.Enum","nullable":false,"package_name":"java.lang","type_parameters":{"E":{"kind":"java","class_name":"DyeColor","display_name":"DyeColor","interfaces":[],"key":"net.minecraft.world.item.DyeColor","nullable":false,"package_name":"net.minecraft.world.item","type_parameters":{}}}},"type_parameters":{}},"version":"1","zen_code_name":"crafttweaker.api.item.component.DyeColor"}