{"kind":"type","display_name":"PlayerAdvancements","extra":{"loaders":["crafttweaker"]},"key":"vanilla/api/advancement/PlayerAdvancements","members":{"award":{"key":"award","members":[{"kind":"method","display_name":"award","extra":{},"key":"award","origin":"native","parameters":[{"display_name":"advancement","key":"advancement","type":{"kind":"java","class_name":"AdvancementHolder","display_name":"AdvancementHolder","interfaces":[],"key":"net.minecraft.advancements.AdvancementHolder","nullable":false,"package_name":"net.minecraft.advancements","type_parameters":{}}},{"display_name":"criteria","key":"criteria","type":{"kind":"basic","display_name":"string","key":"java.lang.String","nullable":false}}],"return_type":{"kind":"basic","display_name":"bool","key":"boolean","nullable":false},"static":false,"type_parameters":{}}]},"flushDirty":{"key":"flushDirty","members":[{"kind":"method","display_name":"flushDirty","extra":{},"key":"flushDirty","origin":"native","parameters":[{"display_name":"player","key":"player","type":{"kind":"java","class_name":"ServerPlayer","display_name":"ServerPlayer","interfaces":[],"key":"net.minecraft.server.level.ServerPlayer","nullable":false,"package_name":"net.minecraft.server.level","type_parameters":{}}}],"return_type":{"kind":"basic","display_name":"void","key":"void","nullable":false},"static":false,"type_parameters":{}}]},"getOrStartProgress":{"key":"getOrStartProgress","members":[{"kind":"method","display_name":"getOrStartProgress","extra":{},"key":"getOrStartProgress","origin":"native","parameters":[{"display_name":"advancement","key":"advancement","type":{"kind":"java","class_name":"AdvancementHolder","display_name":"AdvancementHolder","interfaces":[],"key":"net.minecraft.advancements.AdvancementHolder","nullable":false,"package_name":"net.minecraft.advancements","type_parameters":{}}}],"return_type":{"kind":"java","class_name":"AdvancementProgress","display_name":"AdvancementProgress","interfaces":[],"key":"net.minecraft.advancements.AdvancementProgress","nullable":false,"package_name":"net.minecraft.advancements","type_parameters":{}},"static":false,"type_parameters":{}}]},"revoke":{"key":"revoke","members":[{"kind":"method","display_name":"revoke","extra":{},"key":"revoke","origin":"native","parameters":[{"display_name":"advancement","key":"advancement","type":{"kind":"java","class_name":"AdvancementHolder","display_name":"AdvancementHolder","interfaces":[],"key":"net.minecraft.advancements.AdvancementHolder","nullable":false,"package_name":"net.minecraft.advancements","type_parameters":{}}},{"display_name":"criteria","key":"criteria","type":{"kind":"basic","display_name":"string","key":"java.lang.String","nullable":false}}],"return_type":{"kind":"basic","display_name":"bool","key":"boolean","nullable":false},"static":false,"type_parameters":{}}]}},"type":{"kind":"java","class_name":"PlayerAdvancements","display_name":"PlayerAdvancements","interfaces":[],"key":"net.minecraft.server.PlayerAdvancements","nullable":false,"package_name":"net.minecraft.server","super_type":{"kind":"java","class_name":"Object","display_name":"Object","interfaces":[],"key":"java.lang.Object","nullable":false,"package_name":"java.lang","type_parameters":{}},"type_parameters":{}},"version":"1","zen_code_name":"crafttweaker.api.advancement.PlayerAdvancements"}