{"kind":"type","display_name":"IItemHandler","extra":{"loaders":["crafttweaker"]},"key":"forge/api/capability/IItemHandler","members":{"extractItem":{"key":"extractItem","members":[{"kind":"method","comment":{"kind":"root","children":[{"kind":"plaintext","content":"Extract from the given slot."}]},"display_name":"extractItem","extra":{"examples":{"amount":["5"],"simulate":["false"],"slot":["0"]},"parameter_comment":{"amount":{"kind":"root","children":[{"kind":"plaintext","content":"How much to extract from the slot."}]},"simulate":{"kind":"root","children":[{"kind":"plaintext","content":"If the extraction should actually happen, if true, no changes will be made."}]},"slot":{"kind":"root","children":[{"kind":"plaintext","content":"The slot to extract from."}]}},"returns":{"kind":"root","children":[{"kind":"plaintext","content":"The stack extracted from the slot."}]}},"key":"extractItem","origin":"native","parameters":[{"display_name":"slot","key":"slot","type":{"kind":"basic","display_name":"int","key":"int","nullable":false}},{"display_name":"amount","key":"amount","type":{"kind":"basic","display_name":"int","key":"int","nullable":false}},{"display_name":"simulate","key":"simulate","type":{"kind":"basic","display_name":"bool","key":"boolean","nullable":false}}],"return_type":{"kind":"java","class_name":"IItemStack","display_name":"IItemStack","interfaces":[],"key":"com.blamejared.crafttweaker.api.item.IItemStack","nullable":false,"package_name":"com.blamejared.crafttweaker.api.item","type_parameters":{}},"static":false,"type_parameters":{}}]},"getSlotLimit":{"key":"getSlotLimit","members":[{"kind":"method","comment":{"kind":"root","children":[{"kind":"plaintext","content":"Gets how much of a stack can fit into the given slot."}]},"display_name":"getSlotLimit","extra":{"examples":{"slot":["1"]},"parameter_comment":{"slot":{"kind":"root","children":[{"kind":"plaintext","content":"The slot to check."}]}},"returns":{"kind":"root","children":[{"kind":"plaintext","content":"The max stack size of the given stack."}]}},"key":"getSlotLimit","origin":"native","parameters":[{"display_name":"slot","key":"slot","type":{"kind":"basic","display_name":"int","key":"int","nullable":false}}],"return_type":{"kind":"basic","display_name":"int","key":"int","nullable":false},"static":false,"type_parameters":{}}]},"getStackInSlot":{"key":"getStackInSlot","members":[{"kind":"method","comment":{"kind":"root","children":[{"kind":"plaintext","content":"Gets the stack in the given slot."}]},"display_name":"getStackInSlot","extra":{"examples":{"slot":["1"]},"parameter_comment":{"slot":{"kind":"root","children":[{"kind":"plaintext","content":"The slot to get the stack of."}]}},"returns":{"kind":"root","children":[{"kind":"plaintext","content":"The stack in the slot."}]}},"key":"getStackInSlot","origin":"native","parameters":[{"display_name":"slot","key":"slot","type":{"kind":"basic","display_name":"int","key":"int","nullable":false}}],"return_type":{"kind":"java","class_name":"IItemStack","display_name":"IItemStack","interfaces":[],"key":"com.blamejared.crafttweaker.api.item.IItemStack","nullable":false,"package_name":"com.blamejared.crafttweaker.api.item","type_parameters":{}},"static":false,"type_parameters":{}},{"kind":"operator","comment":{"kind":"root","children":[{"kind":"plaintext","content":"Gets the stack in the given slot."}]},"display_name":"getStackInSlot","extra":{"examples":{"slot":["1"]},"parameter_comment":{"slot":{"kind":"root","children":[{"kind":"plaintext","content":"The slot to get the stack of."}]}},"returns":{"kind":"root","children":[{"kind":"plaintext","content":"The stack in the slot."}]}},"key":"getStackInSlot","operator":"indexget","origin":"native","parameters":[{"display_name":"slot","key":"slot","type":{"kind":"basic","display_name":"int","key":"int","nullable":false}}],"return_type":{"kind":"java","class_name":"IItemStack","display_name":"IItemStack","interfaces":[],"key":"com.blamejared.crafttweaker.api.item.IItemStack","nullable":false,"package_name":"com.blamejared.crafttweaker.api.item","type_parameters":{}},"static":false,"type_parameters":{}}]},"insertItem":{"key":"insertItem","members":[{"kind":"method","comment":{"kind":"root","children":[{"kind":"plaintext","content":"Inserts the stack into the given slot and returns the remainder. "},{"kind":"paragraph","content":[{"kind":"new_line"},{"kind":"plaintext","content":"The remainder returned is how much was not inserted. "}]},{"kind":"new_line"},{"kind":"paragraph","content":[{"kind":"new_line"},{"kind":"plaintext","content":"For example if slot "},{"kind":"code","content":[{"kind":"plaintext","content":"0"}]},{"kind":"plaintext","content":" had "},{"kind":"code","content":[{"kind":"plaintext","content":"63"}]},{"kind":"plaintext","content":" dirt, and you tried to insert "},{"kind":"code","content":[{"kind":"plaintext","content":"5"}]},{"kind":"plaintext","content":" dirt, you will get a remainder of "},{"kind":"code","content":[{"kind":"plaintext","content":"4"}]},{"kind":"plaintext","content":" dirt. "}]}]},"display_name":"insertItem","extra":{"examples":{"simulate":["true"],"slot":["1"],"stack":["\u003citem:minecraft:dirt\u003e"]},"parameter_comment":{"simulate":{"kind":"root","children":[{"kind":"plaintext","content":"If the insert should actually happen, if true, will be made."}]},"slot":{"kind":"root","children":[{"kind":"plaintext","content":"The slot to insert into."}]},"stack":{"kind":"root","children":[{"kind":"plaintext","content":"The stack to insert."}]}},"returns":{"kind":"root","children":[{"kind":"plaintext","content":"The remaining stack that was not inserted."}]}},"key":"insertItem","origin":"native","parameters":[{"display_name":"slot","key":"slot","type":{"kind":"basic","display_name":"int","key":"int","nullable":false}},{"display_name":"stack","key":"stack","type":{"kind":"java","class_name":"IItemStack","display_name":"IItemStack","interfaces":[],"key":"com.blamejared.crafttweaker.api.item.IItemStack","nullable":false,"package_name":"com.blamejared.crafttweaker.api.item","type_parameters":{}}},{"display_name":"simulate","key":"simulate","type":{"kind":"basic","display_name":"bool","key":"boolean","nullable":false}}],"return_type":{"kind":"java","class_name":"IItemStack","display_name":"IItemStack","interfaces":[],"key":"com.blamejared.crafttweaker.api.item.IItemStack","nullable":false,"package_name":"com.blamejared.crafttweaker.api.item","type_parameters":{}},"static":false,"type_parameters":{}}]},"isItemValid":{"key":"isItemValid","members":[{"kind":"method","comment":{"kind":"root","children":[{"kind":"plaintext","content":"Checks if the given stack is valid for the given slot."}]},"display_name":"isItemValid","extra":{"parameter_comment":{"slot":{"kind":"root","children":[{"kind":"plaintext","content":"The slot to check."}]},"stack":{"kind":"root","children":[{"kind":"plaintext","content":"The stack to check."}]}},"returns":{"kind":"root","children":[{"kind":"plaintext","content":"true if the stack is valid, false otherwise."}]}},"key":"isItemValid","origin":"native","parameters":[{"display_name":"slot","key":"slot","type":{"kind":"basic","display_name":"int","key":"int","nullable":false}},{"display_name":"stack","key":"stack","type":{"kind":"java","class_name":"IItemStack","display_name":"IItemStack","interfaces":[],"key":"com.blamejared.crafttweaker.api.item.IItemStack","nullable":false,"package_name":"com.blamejared.crafttweaker.api.item","type_parameters":{}}}],"return_type":{"kind":"basic","display_name":"bool","key":"boolean","nullable":false},"static":false,"type_parameters":{}}]},"slots":{"key":"slots","members":[{"kind":"method","comment":{"kind":"root","children":[{"kind":"plaintext","content":"Gets the amount of slots in the handler."}]},"display_name":"slots","extra":{"returns":{"kind":"root","children":[{"kind":"plaintext","content":"The amount of slots in the handler."}]}},"key":"slots","origin":"native","parameters":[],"return_type":{"kind":"basic","display_name":"int","key":"int","nullable":false},"static":false,"type_parameters":{}},{"kind":"getter","comment":{"kind":"root","children":[{"kind":"plaintext","content":"Gets the amount of slots in the handler."}]},"display_name":"slots","extra":{"returns":{"kind":"root","children":[{"kind":"plaintext","content":"The amount of slots in the handler."}]}},"key":"slots","origin":"native","static":false,"type":{"kind":"basic","display_name":"int","key":"int","nullable":false}}]}},"type":{"kind":"java","class_name":"IItemHandler","display_name":"IItemHandler","interfaces":[],"key":"net.minecraftforge.items.IItemHandler","nullable":false,"package_name":"net.minecraftforge.items","type_parameters":{}},"version":"1","zen_code_name":"crafttweaker.api.capability.IItemHandler"}