{"kind":"type","display_name":"LivingEvent","extra":{"loaders":["crafttweaker"]},"key":"neoforge/api/event/entity/living/LivingEvent","members":{"entity":{"key":"entity","members":[{"kind":"getter","display_name":"entity","extra":{},"key":"entity","origin":"native","static":false,"type":{"kind":"java","class_name":"LivingEntity","display_name":"LivingEntity","interfaces":[],"key":"net.minecraft.world.entity.LivingEntity","nullable":false,"package_name":"net.minecraft.world.entity","type_parameters":{}}}]}},"type":{"kind":"java","class_name":"LivingEvent","display_name":"LivingEvent","interfaces":[],"key":"net.neoforged.neoforge.event.entity.living.LivingEvent","nullable":false,"package_name":"net.neoforged.neoforge.event.entity.living","super_type":{"kind":"java","class_name":"EntityEvent","display_name":"EntityEvent","interfaces":[],"key":"net.neoforged.neoforge.event.entity.EntityEvent","nullable":false,"package_name":"net.neoforged.neoforge.event.entity","type_parameters":{}},"type_parameters":{}},"version":"1","zen_code_name":"crafttweaker.neoforge.api.event.entity.living.LivingEvent"}